betterstack/__init__.py
betterstack/uptime/__init__.py
betterstack/uptime/auth/__init__.py
betterstack/uptime/helpers/__init__.py
betterstack/uptime/mixins/__init__.py
betterstack/uptime/objects/__init__.py
betterstack_uptime-1.0.3.dist-info/LICENCE.md
betterstack_uptime-1.0.3.dist-info/METADATA
betterstack_uptime-1.0.3.dist-info/WHEEL
betterstack_uptime-1.0.3.dist-info/top_level.txt
betterstack_uptime-1.0.3.dist-info/RECORD
