Metadata-Version: 2.1
Name: betterstack-uptime
Version: 1.0.3
Summary: Library for communicating with the BetterStack Uptime API
Home-page: https://github.com/iwink/python-betterstack-uptime
Author: iWink
Author-email: hosting@iwink.nl
Classifier: Programming Language :: Python :: 3
Classifier: License :: OSI Approved :: MIT License
Classifier: Operating System :: OS Independent
Classifier: License :: OSI Approved :: GNU General Public License v3 (GPLv3)
Requires-Python: >=3
License-File: LICENCE.md
Requires-Dist: requests
